jdif/__init__.py
jdif/display.py
json_diff_cli-1.0.2.dist-info/LICENSE
json_diff_cli-1.0.2.dist-info/METADATA
json_diff_cli-1.0.2.dist-info/WHEEL
json_diff_cli-1.0.2.dist-info/entry_points.txt
json_diff_cli-1.0.2.dist-info/top_level.txt
json_diff_cli-1.0.2.dist-info/RECORD
