Metadata-Version: 2.1
Name: json-diff-cli
Version: 1.0.2
Summary: To display json differences on CLI
Author: shivani
License: MIT
Project-URL: Source, https://github.com/Shivani-20/json-diff-cli
Keywords: json,diff
Classifier: Programming Language :: Python :: 3.12
Classifier: License :: OSI Approved :: MIT License
Classifier: Operating System :: OS Independent
Classifier: Intended Audience :: Developers
Classifier: Topic :: File Formats :: JSON
Classifier: Topic :: File Formats :: JSON :: JSON Schema
Classifier: Topic :: Software Development :: Debuggers
Classifier: Environment :: Console
Requires-Python: >=3.8
License-File: LICENSE
Requires-Dist: termcolor>=2.4.0
Requires-Dist: deepdiff>=7.0.1
Requires-Dist: charade>=1.0.3
Requires-Dist: pyparsing>=3.1.2
